django_ynh/__init__.py
django_ynh/base_settings.py
django_ynh/local_test.py
django_ynh/management/__init__.py
django_ynh/management/commands/__init__.py
django_ynh/management/commands/create_superuser.py
django_ynh/path_utils.py
django_ynh/pytest_helper.py
django_ynh/secret_key.py
django_ynh/sso_auth/__init__.py
django_ynh/sso_auth/auth_backend.py
django_ynh/sso_auth/auth_middleware.py
django_ynh/sso_auth/user_profile.py
django_ynh/test_utils.py
django_ynh/views.py
django_ynh-0.1.5.dist-info/LICENSE
django_ynh-0.1.5.dist-info/WHEEL
django_ynh-0.1.5.dist-info/METADATA
django_ynh-0.1.5.dist-info/RECORD
