Metadata-Version: 2.1
Name: django-ynh
Version: 0.1.5
Summary: Glue code to package django projects as yunohost apps.
Home-page: https://github.com/YunoHost-Apps/django_ynh
License: GPL
Author: JensDiemer
Author-email: git@jensdiemer.de
Requires-Python: >=3.7,<4.0.0
Classifier: License :: Other/Proprietary License
Classifier: Programming Language :: Python :: 3
Classifier: Programming Language :: Python :: 3.7
Classifier: Programming Language :: Python :: 3.8
Classifier: Programming Language :: Python :: 3.9
Provides-Extra: ynh
Requires-Dist: django
Requires-Dist: django-axes; extra == "ynh"
Requires-Dist: django-redis; extra == "ynh"
Requires-Dist: gunicorn; extra == "ynh"
Requires-Dist: psycopg2-binary; extra == "ynh"
